datefun/__init__.py
datefun/datefun.py
datefun-0.0.8.dist-info/METADATA
datefun-0.0.8.dist-info/WHEEL
datefun-0.0.8.dist-info/licenses/LICENSE.txt
datefun-0.0.8.dist-info/RECORD
