Metadata-Version: 2.4
Name: datefun
Version: 0.0.8
Summary: Functional approach to dates (as ISO-DATE string)
Author: Nauri Nastik
License-File: LICENSE.txt
Classifier: License :: OSI Approved :: MIT License
Classifier: Operating System :: OS Independent
Classifier: Programming Language :: Python :: 3
Requires-Python: >=3.10
